spice/__init__.py
spice/geometry/__init__.py
spice/geometry/sutherland_hodgman.py
spice/geometry/utils.py
spice/icosphere_cache/icosphere_1.pickle
spice/icosphere_cache/icosphere_2.pickle
spice/icosphere_cache/icosphere_3.pickle
spice/icosphere_cache/icosphere_4.pickle
spice/icosphere_cache/icosphere_5.pickle
spice/models/__init__.py
spice/models/binary.py
spice/models/mesh_generation.py
spice/models/mesh_model.py
spice/models/mesh_transform.py
spice/models/mesh_view.py
spice/models/mesh_view_kdtree.py
spice/models/model.py
spice/models/orbit_utils.py
spice/models/phoebe_model.py
spice/models/phoebe_utils.py
spice/models/spots.py
spice/models/utils.py
spice/phoebe_model/DI-Her-meshes.py
spice/plots/__init__.py
spice/plots/plot_mesh.py
spice/spectrum/__init__.py
spice/spectrum/atlas9_interpolator.py
spice/spectrum/filter.py
spice/spectrum/planck_law.py
spice/spectrum/spectrum.py
spice/spectrum/spectrum_emulator.py
spice/spectrum/spectrum_korg.py
spice/spectrum/user_spectrum_interpolator.py
spice/spectrum/utils.py
spice/spectrum/filter_data/2MASSH.dat
spice/spectrum/filter_data/2MASSJ.dat
spice/spectrum/filter_data/2MASSK.dat
spice/spectrum/filter_data/GALEXFUV.dat
spice/spectrum/filter_data/GALEXNUV.dat
spice/spectrum/filter_data/LSSTg.dat
spice/spectrum/filter_data/LSSTi.dat
spice/spectrum/filter_data/LSSTr.dat
spice/spectrum/filter_data/LSSTu.dat
spice/spectrum/filter_data/LSSTy.dat
spice/spectrum/filter_data/LSSTz.dat
spice/spectrum/filter_data/SDSS.dat
spice/spectrum/filter_data/__init__.py
spice/spectrum/filter_data/gaia_edr3_passband.dat
spice/spectrum/filter_data/gaia_edr3_zeropt.dat
spice/spectrum/filter_data/grvsfilter.csv
spice/spectrum/filter_data/panstarrs.dat
spice/utils/__init__.py
spice/utils/fourier_fit.py
spice/utils/parameters.py
spice/utils/warnings.py
stellar_spice-1.5.7.dist-info/METADATA
stellar_spice-1.5.7.dist-info/WHEEL
stellar_spice-1.5.7.dist-info/top_level.txt
stellar_spice-1.5.7.dist-info/RECORD
