Metadata-Version: 2.4
Name: stellar-spice
Version: 1.5.7
Requires-Dist: autofig~=1.2.0
Requires-Dist: chex~=0.1.88
Requires-Dist: cmasher~=1.9.2
Requires-Dist: jaxtyping~=0.2.36
Requires-Dist: jax>=0.4.38
Requires-Dist: jaxlib>=0.4.38
Requires-Dist: numpy~=1.26.4
Requires-Dist: overrides~=7.7.0
Requires-Dist: flax>=0.10.4
Requires-Dist: joblib~=1.3.2
Requires-Dist: transformer-payne~=0.9
Requires-Dist: h5py~=3.13.0
Provides-Extra: huggingface
Requires-Dist: huggingface-hub~=0.21.3; extra == "huggingface"
Provides-Extra: dev
Requires-Dist: pytest~=8.0.0; extra == "dev"
Requires-Dist: pytest-datadir~=1.5.0; extra == "dev"
Requires-Dist: coverage~=7.4.3; extra == "dev"
Provides-Extra: phoebe
Requires-Dist: phoebe~=2.4.17; extra == "phoebe"
